protobufferize/__init__.py
protobufferize-2.0.dist-info/LICENSE.txt
protobufferize-2.0.dist-info/METADATA
protobufferize-2.0.dist-info/WHEEL
protobufferize-2.0.dist-info/entry_points.txt
protobufferize-2.0.dist-info/top_level.txt
protobufferize-2.0.dist-info/RECORD
