Metadata-Version: 2.1
Name: protobufferize
Version: 2.0
Summary: Compile protobuffers with setuptools
Home-page: https://github.com/pierlauro/protobufferize
Author: pierlauro
Author-email: foss@pstux.dev
License: GNU Affero General Public License v3.0
Project-URL: Bug Tracker, https://github.com/pierlauro/protobufferize/issues
Project-URL: Source, https://github.com/pierlauro/protobufferize
Keywords: protocolbuffer proto protobuf grpc setuptools protobufferize
Platform: UNKNOWN
Classifier: Development Status :: 5 - Production/Stable
Classifier: Intended Audience :: Developers
Classifier: Programming Language :: Python :: 3.6
Classifier: Programming Language :: Python :: 3.7
Requires-Python: >=3.6
Requires-Dist: distro
Requires-Dist: grpc-tools
Requires-Dist: mock
Requires-Dist: xmltodict
